mock_pyserial/__init__.py
mock_pyserial/_version.py
mock_pyserial/mock_serial.py
mock_pyserial/tests/__init__.py
mock_pyserial/tests/conftest.py
mock_pyserial/tests/test_examples.py
mock_pyserial-0.0.0.dist-info/AUTHORS.rst
mock_pyserial-0.0.0.dist-info/LICENSE
mock_pyserial-0.0.0.dist-info/METADATA
mock_pyserial-0.0.0.dist-info/WHEEL
mock_pyserial-0.0.0.dist-info/entry_points.txt
mock_pyserial-0.0.0.dist-info/top_level.txt
mock_pyserial-0.0.0.dist-info/RECORD
