Metadata-Version: 2.1
Name: mock-pyserial
Version: 0.0.0
Summary: Mock Pyserial project for isntrumentation
Home-page: https://github.com/vstadnytskyi/mock-pyserial
Author: Valentyn Stadnytskyi
Author-email: v.stadnytskyi@gmail.com
License: BSD (3-clause)
Platform: UNKNOWN
Classifier: Development Status :: 2 - Pre-Alpha
Classifier: Natural Language :: English
Classifier: Programming Language :: Python :: 3
Requires-Python: >=3.6
